stahmctestt/__init__.py
stahmctestt-2.0.dist-info/LICENSE
stahmctestt-2.0.dist-info/METADATA
stahmctestt-2.0.dist-info/WHEEL
stahmctestt-2.0.dist-info/top_level.txt
stahmctestt-2.0.dist-info/RECORD
