Metadata-Version: 2.1
Name: stahmctestt
Version: 2.0
Summary: testversion
Home-page: https://github.com/RihuiOu95/HMC.git
Author: TZ RO 
Author-email: thuizhou@outlook.com
License: UNKNOWN
Platform: UNKNOWN
